crosscheck/__init__.py
crosscheck/_version.py
crosscheck/crosscheck_plugin.py
crosscheck/static/extension.js
crosscheck/static/index.js
crosscheck/static/index.js.map
crosscheck_widget-0.1.0a0.data/data/etc/jupyter/nbconfig/notebook.d/crosscheck-widget.json
crosscheck_widget-0.1.0a0.data/data/share/jupyter/nbextensions/crosscheck-widget/extension.js
crosscheck_widget-0.1.0a0.data/data/share/jupyter/nbextensions/crosscheck-widget/index.js
crosscheck_widget-0.1.0a0.data/data/share/jupyter/nbextensions/crosscheck-widget/index.js.map
crosscheck_widget-0.1.0a0.dist-info/METADATA
crosscheck_widget-0.1.0a0.dist-info/WHEEL
crosscheck_widget-0.1.0a0.dist-info/top_level.txt
crosscheck_widget-0.1.0a0.dist-info/RECORD
